LICENSE
README.md
setup.py
datalidator/DatalidatorConstants.py
datalidator/DatalidatorObjectIface.py
datalidator/DefaultDatalidatorObjectImplBase.py
datalidator/__init__.py
datalidator.egg-info/PKG-INFO
datalidator.egg-info/SOURCES.txt
datalidator.egg-info/dependency_links.txt
datalidator.egg-info/top_level.txt
datalidator/blueprints/BlueprintIface.py
datalidator/blueprints/DataConversionHelper.py
datalidator/blueprints/DefaultBlueprintImplBase.py
datalidator/blueprints/DefaultBlueprintWithModeSupportImplBase.py
datalidator/blueprints/DefaultBlueprintWithStandardFeaturesImplBase.py
datalidator/blueprints/ParsingMode.py
datalidator/blueprints/__init__.py
datalidator/blueprints/exc/BlueprintExc.py
datalidator/blueprints/exc/InputDataNotConvertibleExc.py
datalidator/blueprints/exc/InputDataNotUnsubclassableExc.py
datalidator/blueprints/exc/InputDataTypeInBlocklistExc.py
datalidator/blueprints/exc/InputDataTypeNotInAllowlistExc.py
datalidator/blueprints/exc/InputDataValueNotAllowedForDataTypeExc.py
datalidator/blueprints/exc/InvalidInputDataExc.py
datalidator/blueprints/exc/UnexpectedExceptionRaisedInBlueprintExc.py
datalidator/blueprints/exc/UnexpectedOutputDataTypeExc.py
datalidator/blueprints/exc/__init__.py
datalidator/blueprints/exc/err/BlueprintError.py
datalidator/blueprints/exc/err/InvalidBlueprintConfigError.py
datalidator/blueprints/exc/err/__init__.py
datalidator/blueprints/exc/utils/InvalidInputDataExcFactory.py
datalidator/blueprints/exc/utils/__init__.py
datalidator/blueprints/extras/ObjectModel.py
datalidator/blueprints/extras/OptionalItem.py
datalidator/blueprints/extras/OptionalItemIface.py
datalidator/blueprints/extras/__init__.py
datalidator/blueprints/impl/BooleanBlueprint.py
datalidator/blueprints/impl/BytesBlueprint.py
datalidator/blueprints/impl/DateBlueprint.py
datalidator/blueprints/impl/DatetimeBlueprint.py
datalidator/blueprints/impl/DictionaryBlueprint.py
datalidator/blueprints/impl/FloatBlueprint.py
datalidator/blueprints/impl/GenericBlueprint.py
datalidator/blueprints/impl/IPAddressBlueprint.py
datalidator/blueprints/impl/IPNetworkBlueprint.py
