Metadata-Version: 2.1
Name: datalidator
Version: 1.0.3
Summary: A flexible, object-oriented Python input data parsing & validation library
Home-page: https://github.com/vitlabuda/datalidator
Author: Vít Labuda
Author-email: dev@vitlabuda.cz
License: BSD License
Project-URL: Bug Tracker, https://github.com/vitlabuda/datalidator/issues
Platform: UNKNOWN
Classifier: Development Status :: 5 - Production/Stable
Classifier: Intended Audience :: Developers
Classifier: License :: OSI Approved :: BSD License
Classifier: Operating System :: OS Independent
Classifier: Programming Language :: Python :: 3
Classifier: Programming Language :: Python :: 3.9
Classifier: Programming Language :: Python :: 3.10
Classifier: Programming Language :: Python :: 3.11
Classifier: Topic :: Software Development :: Libraries
Classifier: Typing :: Typed
Requires-Python: >=3.9
License-File: LICENSE
